[
  {
    "pays": "USA",
    "citations": 257
  },
  {
    "pays": "FRA",
    "citations": 148
  },
  {
    "pays": "IRN",
    "citations": 137
  },
  {
    "pays": "UKR",
    "citations": 115
  },
  {
    "pays": "RUS",
    "citations": 88
  },
  {
    "pays": "GBR",
    "citations": 69
  },
  {
    "pays": "ISR",
    "citations": 62
  },
  {
    "pays": "CHN",
    "citations": 42
  },
  {
    "pays": "MAR",
    "citations": 34
  },
  {
    "pays": "DEU",
    "citations": 23
  },
  {
    "pays": "LBN",
    "citations": 16
  },
  {
    "pays": "TUR",
    "citations": 14
  },
  {
    "pays": "IND",
    "citations": 13
  },
  {
    "pays": "DZA",
    "citations": 10
  },
  {
    "pays": "JPN",
    "citations": 9
  },
  {
    "pays": "MLI",
    "citations": 7
  },
  {
    "pays": "BRA",
    "citations": 6
  },
  {
    "pays": "CAF",
    "citations": 3
  },
  {
    "pays": "NER",
    "citations": 3
  },
  {
    "pays": "BFA",
    "citations": 2
  }
]