{
  "BFA": [
    {
      "mot": "sahel",
      "score": 13.79
    },
    {
      "mot": "filmer",
      "score": 12.4
    },
    {
      "mot": "burkina",
      "score": 12.4
    },
    {
      "mot": "faso",
      "score": 12.4
    },
    {
      "mot": "niger",
      "score": 11.59
    },
    {
      "mot": "poursuivre",
      "score": 11.02
    },
    {
      "mot": "interdit",
      "score": 9.39
    },
    {
      "mot": "pauvres",
      "score": 6.89
    },
    {
      "mot": "lavrov",
      "score": 6.89
    },
    {
      "mot": "juntes",
      "score": 6.89
    },
    {
      "mot": "regroupe",
      "score": 6.89
    },
    {
      "mot": "putschistes",
      "score": 6.89
    },
    {
      "mot": "accordes",
      "score": 6.89
    },
    {
      "mot": "domaines",
      "score": 6.89
    },
    {
      "mot": "russe",
      "score": 6.74
    }
  ],
  "BRA": [
    {
      "mot": "bresil",
      "score": 23.18
    },
    {
      "mot": "jair",
      "score": 18.6
    },
    {
      "mot": "bolsonaro",
      "score": 18.6
    },
    {
      "mot": "assigne",
      "score": 18.6
    },
    {
      "mot": "residence",
      "score": 16.53
    },
    {
      "mot": "argentin",
      "score": 15.31
    },
    {
      "mot": "visite",
      "score": 12.99
    },
    {
      "mot": "bresilienne",
      "score": 12.4
    },
    {
      "mot": "bresilien",
      "score": 12.4
    },
    {
      "mot": "bresiliennes",
      "score": 12.4
    },
    {
      "mot": "taxer",
      "score": 12.4
    },
    {
      "mot": "normes",
      "score": 11.02
    },
    {
      "mot": "javier",
      "score": 10.57
    },
    {
      "mot": "milei",
      "score": 10.57
    },
    {
      "mot": "douane",
      "score": 10.57
    }
  ],
  "CAF": [
    {
      "mot": "centrafrique",
      "score": 18.6
    },
    {
      "mot": "wagner",
      "score": 12.4
    },
    {
      "mot": "refuser",
      "score": 12.4
    },
    {
      "mot": "asile",
      "score": 12.4
    },
    {
      "mot": "ephrem",
      "score": 12.4
    },
    {
      "mot": "yalike",
      "score": 12.4
    },
    {
      "mot": "ngonzo",
      "score": 12.4
    },
    {
      "mot": "propagande",
      "score": 11.59
    },
    {
      "mot": "lanceur",
      "score": 10.57
    },
    {
      "mot": "france",
      "score": 10.31
    },
    {
      "mot": "russe",
      "score": 10.1
    },
    {
      "mot": "voit",
      "score": 9.63
    },
    {
      "mot": "participe",
      "score": 9.63
    },
    {
      "mot": "denonce",
      "score": 8.01
    },
    {
      "mot": "alerte",
      "score": 7.7
    }
  ],
  "CHN": [
    {
      "mot": "chine",
      "score": 163.63
    },
    {
      "mot": "typhon",
      "score": 47.57
    },
    {
      "mot": "chinois",
      "score": 44.54
    },
    {
      "mot": "chinoise",
      "score": 42.28
    },
    {
      "mot": "pekin",
      "score": 38.52
    },
    {
      "mot": "brumisateurs",
      "score": 34.78
    },
    {
      "mot": "canal",
      "score": 34.78
    },
    {
      "mot": "immeubles",
      "score": 31.71
    },
    {
      "mot": "jinping",
      "score": 31.71
    },
    {
      "mot": "bavi",
      "score": 31.71
    },
    {
      "mot": "usine",
      "score": 26.43
    },
    {
      "mot": "shanghai",
      "score": 26.43
    },
    {
      "mot": "ports",
      "score": 23.39
    },
    {
      "mot": "chaussures",
      "score": 23.18
    },
    {
      "mot": "panama",
      "score": 23.18
    }
  ],
  "DEU": [
    {
      "mot": "allemagne",
      "score": 63.83
    },
    {
      "mot": "berlin",
      "score": 48.15
    },
    {
      "mot": "allemand",
      "score": 46.97
    },
    {
      "mot": "conseil",
      "score": 28.89
    },
    {
      "mot": "allemande",
      "score": 26.43
    },
    {
      "mot": "friedrich",
      "score": 26.43
    },
    {
      "mot": "merz",
      "score": 26.43
    },
    {
      "mot": "chancelier",
      "score": 25.51
    },
    {
      "mot": "jens",
      "score": 23.18
    },
    {
      "mot": "spahn",
      "score": 23.18
    },
    {
      "mot": "franco",
      "score": 22.05
    },
    {
      "mot": "homme",
      "score": 19.49
    },
    {
      "mot": "uber",
      "score": 18.6
    },
    {
      "mot": "presse",
      "score": 18.37
    },
    {
      "mot": "cooperation",
      "score": 18.37
    }
  ],
  "DZA": [
    {
      "mot": "algerie",
      "score": 48.15
    },
    {
      "mot": "alger",
      "score": 27.54
    },
    {
      "mot": "christophe",
      "score": 23.18
    },
    {
      "mot": "gleizes",
      "score": 23.18
    },
    {
      "mot": "algerien",
      "score": 22.03
    },
    {
      "mot": "mali",
      "score": 19.8
    },
    {
      "mot": "journaliste",
      "score": 15.04
    },
    {
      "mot": "liberation",
      "score": 14.85
    },
    {
      "mot": "esperent",
      "score": 13.79
    },
    {
      "mot": "visas",
      "score": 13.79
    },
    {
      "mot": "kidal",
      "score": 13.79
    },
    {
      "mot": "paris",
      "score": 12.63
    },
    {
      "mot": "orphelinat",
      "score": 12.4
    },
    {
      "mot": "mohammadia",
      "score": 12.4
    },
    {
      "mot": "accelerer",
      "score": 12.4
    }
  ],
  "FRA": [
    {
      "mot": "france",
      "score": 252.56
    },
    {
      "mot": "francais",
      "score": 164.4
    },
    {
      "mot": "paris",
      "score": 142.07
    },
    {
      "mot": "maroc",
      "score": 121.26
    },
    {
      "mot": "francaise",
      "score": 101.82
    },
    {
      "mot": "emmanuel",
      "score": 101.5
    },
    {
      "mot": "macron",
      "score": 101.5
    },
    {
      "mot": "juillet",
      "score": 84.39
    },
    {
      "mot": "monde",
      "score": 72.32
    },
    {
      "mot": "coalition",
      "score": 72.27
    },
    {
      "mot": "defile",
      "score": 68.09
    },
    {
      "mot": "volontaires",
      "score": 68.07
    },
    {
      "mot": "espagne",
      "score": 63.17
    },
    {
      "mot": "incendie",
      "score": 60.06
    },
    {
      "mot": "dernier",
      "score": 59.97
    }
  ],
  "GBR": [
    {
      "mot": "uni",
      "score": 131.36
    },
    {
      "mot": "royaume",
      "score": 122.21
    },
    {
      "mot": "britannique",
      "score": 97.74
    },
    {
      "mot": "angleterre",
      "score": 89.35
    },
    {
      "mot": "andy",
      "score": 74.97
    },
    {
      "mot": "burnham",
      "score": 74.97
    },
    {
      "mot": "tapisserie",
      "score": 72.23
    },
    {
      "mot": "british",
      "score": 71.95
    },
    {
      "mot": "londres",
      "score": 71.17
    },
    {
      "mot": "bayeux",
      "score": 62.6
    },
    {
      "mot": "keir",
      "score": 55.11
    },
    {
      "mot": "starmer",
      "score": 55.11
    },
    {
      "mot": "museum",
      "score": 52.97
    },
    {
      "mot": "ministre",
      "score": 52.2
    },
    {
      "mot": "argentine",
      "score": 49.45
    }
  ],
  "IND": [
    {
      "mot": "inde",
      "score": 64.95
    },
    {
      "mot": "indien",
      "score": 27.54
    },
    {
      "mot": "greve",
      "score": 27.54
    },
    {
      "mot": "faim",
      "score": 26.43
    },
    {
      "mot": "examens",
      "score": 26.43
    },
    {
      "mot": "sonam",
      "score": 23.18
    },
    {
      "mot": "wangchuk",
      "score": 23.18
    },
    {
      "mot": "cafards",
      "score": 22.03
    },
    {
      "mot": "port",
      "score": 19.8
    },
    {
      "mot": "fraudes",
      "score": 17.39
    },
    {
      "mot": "delhi",
      "score": 17.39
    },
    {
      "mot": "ocean",
      "score": 17.39
    },
    {
      "mot": "force",
      "score": 16.75
    },
    {
      "mot": "manifestation",
      "score": 15.31
    },
    {
      "mot": "new",
      "score": 15.04
    }
  ],
  "IRN": [
    {
      "mot": "iran",
      "score": 383.13
    },
    {
      "mot": "moyen",
      "score": 217.5
    },
    {
      "mot": "orient",
      "score": 217.5
    },
    {
      "mot": "frappes",
      "score": 182.01
    },
    {
      "mot": "unis",
      "score": 176.46
    },
    {
      "mot": "etats",
      "score": 173.41
    },
    {
      "mot": "teheran",
      "score": 161.06
    },
    {
      "mot": "guerre",
      "score": 159.73
    },
    {
      "mot": "detroit",
      "score": 138.13
    },
    {
      "mot": "armee",
      "score": 134.49
    },
    {
      "mot": "americaines",
      "score": 131.61
    },
    {
      "mot": "nuit",
      "score": 131.32
    },
    {
      "mot": "ormuz",
      "score": 130.01
    },
    {
      "mot": "direct",
      "score": 123.66
    },
    {
      "mot": "americaine",
      "score": 118.32
    }
  ],
  "ISR": [
    {
      "mot": "israel",
      "score": 138.1
    },
    {
      "mot": "israelienne",
      "score": 110.61
    },
    {
      "mot": "gaza",
      "score": 97.17
    },
    {
      "mot": "israelien",
      "score": 70.08
    },
    {
      "mot": "israeliennes",
      "score": 66.99
    },
    {
      "mot": "netanyahou",
      "score": 66.15
    },
    {
      "mot": "benyamin",
      "score": 62.95
    },
    {
      "mot": "liban",
      "score": 61.83
    },
    {
      "mot": "armee",
      "score": 54.71
    },
    {
      "mot": "palestiniens",
      "score": 53.59
    },
    {
      "mot": "hamas",
      "score": 51.67
    },
    {
      "mot": "palestinien",
      "score": 44.97
    },
    {
      "mot": "iran",
      "score": 44.6
    },
    {
      "mot": "bande",
      "score": 37.58
    },
    {
      "mot": "colonies",
      "score": 37.0
    }
  ],
  "JPN": [
    {
      "mot": "japon",
      "score": 59.7
    },
    {
      "mot": "parents",
      "score": 28.98
    },
    {
      "mot": "imperiale",
      "score": 23.18
    },
    {
      "mot": "succession",
      "score": 18.6
    },
    {
      "mot": "tokyo",
      "score": 17.39
    },
    {
      "mot": "apprennent",
      "score": 13.79
    },
    {
      "mot": "ours",
      "score": 13.79
    },
    {
      "mot": "equipent",
      "score": 13.79
    },
    {
      "mot": "frigos",
      "score": 13.79
    },
    {
      "mot": "japonais",
      "score": 13.79
    },
    {
      "mot": "chaudes",
      "score": 13.79
    },
    {
      "mot": "hommes",
      "score": 13.49
    },
    {
      "mot": "nippon",
      "score": 12.4
    },
    {
      "mot": "japan",
      "score": 12.4
    },
    {
      "mot": "expo",
      "score": 12.4
    }
  ],
  "LBN": [
    {
      "mot": "liban",
      "score": 82.44
    },
    {
      "mot": "libanais",
      "score": 44.54
    },
    {
      "mot": "aoun",
      "score": 42.28
    },
    {
      "mot": "joseph",
      "score": 35.72
    },
    {
      "mot": "israel",
      "score": 33.68
    },
    {
      "mot": "sud",
      "score": 25.77
    },
    {
      "mot": "libanaise",
      "score": 22.03
    },
    {
      "mot": "accord",
      "score": 21.82
    },
    {
      "mot": "rencontre",
      "score": 20.02
    },
    {
      "mot": "zones",
      "score": 19.26
    },
    {
      "mot": "armee",
      "score": 18.24
    },
    {
      "mot": "guerre",
      "score": 17.4
    },
    {
      "mot": "pilotes",
      "score": 17.39
    },
    {
      "mot": "president",
      "score": 16.34
    },
    {
      "mot": "washington",
      "score": 16.29
    }
  ],
  "MAR": [
    {
      "mot": "maroc",
      "score": 161.68
    },
    {
      "mot": "france",
      "score": 77.32
    },
    {
      "mot": "atlas",
      "score": 50.51
    },
    {
      "mot": "lions",
      "score": 47.63
    },
    {
      "mot": "equipe",
      "score": 42.35
    },
    {
      "mot": "bleus",
      "score": 40.61
    },
    {
      "mot": "enquete",
      "score": 40.0
    },
    {
      "mot": "coupe",
      "score": 38.77
    },
    {
      "mot": "finale",
      "score": 35.83
    },
    {
      "mot": "jeudi",
      "score": 35.79
    },
    {
      "mot": "quarts",
      "score": 34.64
    },
    {
      "mot": "monde",
      "score": 31.64
    },
    {
      "mot": "franco",
      "score": 30.87
    },
    {
      "mot": "marocain",
      "score": 30.62
    },
    {
      "mot": "boston",
      "score": 28.98
    }
  ],
  "MLI": [
    {
      "mot": "mali",
      "score": 44.54
    },
    {
      "mot": "independantistes",
      "score": 31.71
    },
    {
      "mot": "azawad",
      "score": 18.6
    },
    {
      "mot": "niger",
      "score": 17.39
    },
    {
      "mot": "djihadistes",
      "score": 17.39
    },
    {
      "mot": "liberation",
      "score": 14.85
    },
    {
      "mot": "jihadistes",
      "score": 13.79
    },
    {
      "mot": "sahel",
      "score": 13.79
    },
    {
      "mot": "kidal",
      "score": 13.79
    },
    {
      "mot": "front",
      "score": 13.78
    },
    {
      "mot": "nord",
      "score": 12.53
    },
    {
      "mot": "anefis",
      "score": 12.4
    },
    {
      "mot": "fla",
      "score": 12.4
    },
    {
      "mot": "bamako",
      "score": 12.4
    },
    {
      "mot": "groupes",
      "score": 11.59
    }
  ],
  "NER": [
    {
      "mot": "niger",
      "score": 23.18
    },
    {
      "mot": "sahel",
      "score": 13.79
    },
    {
      "mot": "otages",
      "score": 12.4
    },
    {
      "mot": "poursuivre",
      "score": 11.02
    },
    {
      "mot": "rapprochement",
      "score": 11.02
    },
    {
      "mot": "mali",
      "score": 9.9
    },
    {
      "mot": "diplomatique",
      "score": 9.63
    },
    {
      "mot": "lavrov",
      "score": 6.89
    },
    {
      "mot": "juntes",
      "score": 6.89
    },
    {
      "mot": "regroupe",
      "score": 6.89
    },
    {
      "mot": "putschistes",
      "score": 6.89
    },
    {
      "mot": "accordes",
      "score": 6.89
    },
    {
      "mot": "domaines",
      "score": 6.89
    },
    {
      "mot": "fermete",
      "score": 6.89
    },
    {
      "mot": "tragedie",
      "score": 6.89
    }
  ],
  "RUS": [
    {
      "mot": "russes",
      "score": 169.37
    },
    {
      "mot": "ukraine",
      "score": 165.94
    },
    {
      "mot": "russe",
      "score": 144.84
    },
    {
      "mot": "russie",
      "score": 142.17
    },
    {
      "mot": "drones",
      "score": 118.22
    },
    {
      "mot": "kiev",
      "score": 91.34
    },
    {
      "mot": "guerre",
      "score": 86.98
    },
    {
      "mot": "missiles",
      "score": 80.35
    },
    {
      "mot": "moscou",
      "score": 75.05
    },
    {
      "mot": "ukrainiens",
      "score": 71.1
    },
    {
      "mot": "ukrainiennes",
      "score": 69.04
    },
    {
      "mot": "direct",
      "score": 68.92
    },
    {
      "mot": "ukrainienne",
      "score": 67.69
    },
    {
      "mot": "attaque",
      "score": 55.19
    },
    {
      "mot": "frappes",
      "score": 55.08
    }
  ],
  "TUR": [
    {
      "mot": "turquie",
      "score": 34.64
    },
    {
      "mot": "turc",
      "score": 31.71
    },
    {
      "mot": "missiles",
      "score": 31.44
    },
    {
      "mot": "otan",
      "score": 30.87
    },
    {
      "mot": "sommet",
      "score": 28.85
    },
    {
      "mot": "ankara",
      "score": 17.39
    },
    {
      "mot": "recep",
      "score": 17.39
    },
    {
      "mot": "tayyip",
      "score": 17.39
    },
    {
      "mot": "erdogan",
      "score": 17.39
    },
    {
      "mot": "islamique",
      "score": 17.02
    },
    {
      "mot": "musee",
      "score": 16.53
    },
    {
      "mot": "iran",
      "score": 16.22
    },
    {
      "mot": "donald",
      "score": 15.89
    },
    {
      "mot": "patriot",
      "score": 15.86
    },
    {
      "mot": "trump",
      "score": 15.23
    }
  ],
  "UKR": [
    {
      "mot": "ukraine",
      "score": 303.12
    },
    {
      "mot": "kiev",
      "score": 158.32
    },
    {
      "mot": "zelensky",
      "score": 154.4
    },
    {
      "mot": "russes",
      "score": 149.83
    },
    {
      "mot": "volodymyr",
      "score": 149.3
    },
    {
      "mot": "ukrainien",
      "score": 129.13
    },
    {
      "mot": "guerre",
      "score": 124.94
    },
    {
      "mot": "drones",
      "score": 111.65
    },
    {
      "mot": "direct",
      "score": 111.49
    },
    {
      "mot": "ministre",
      "score": 106.78
    },
    {
      "mot": "defense",
      "score": 104.39
    },
    {
      "mot": "ukrainienne",
      "score": 103.31
    },
    {
      "mot": "russie",
      "score": 96.93
    },
    {
      "mot": "missiles",
      "score": 94.32
    },
    {
      "mot": "russe",
      "score": 94.31
    }
  ],
  "USA": [
    {
      "mot": "unis",
      "score": 335.85
    },
    {
      "mot": "etats",
      "score": 335.76
    },
    {
      "mot": "iran",
      "score": 330.42
    },
    {
      "mot": "trump",
      "score": 291.61
    },
    {
      "mot": "donald",
      "score": 270.09
    },
    {
      "mot": "americain",
      "score": 223.92
    },
    {
      "mot": "moyen",
      "score": 212.92
    },
    {
      "mot": "orient",
      "score": 212.92
    },
    {
      "mot": "americaine",
      "score": 187.1
    },
    {
      "mot": "frappes",
      "score": 170.04
    },
    {
      "mot": "detroit",
      "score": 168.16
    },
    {
      "mot": "guerre",
      "score": 154.98
    },
    {
      "mot": "ormuz",
      "score": 151.17
    },
    {
      "mot": "americains",
      "score": 151.11
    },
    {
      "mot": "armee",
      "score": 148.17
    }
  ]
}