{
  "_source": "lemonde_intl",
  "_url_collecte": "https://www.lemonde.fr/international/rss_full.xml",
  "_capte_le": "2026-07-16T20:56:19.144126+00:00",
  "_id": "0ca88c23ed49",
  "brut": {
    "title": "L’allocution de Donald Trump va porter « sur la protection de l’intégrité » des élections, à l’approche des midterms, dit la Maison Blanche",
    "title_detail": {
      "type": "text/plain",
      "language": null,
      "base": "https://www.lemonde.fr/international/rss_full.xml",
      "value": "L’allocution de Donald Trump va porter « sur la protection de l’intégrité » des élections, à l’approche des midterms, dit la Maison Blanche"
    },
    "published": "Thu, 16 Jul 2026 20:44:38 +0200",
    "published_parsed": [
      2026,
      7,
      16,
      18,
      44,
      38,
      3,
      197,
      0
    ],
    "updated": "Thu, 16 Jul 2026 21:17:05 +0200",
    "updated_parsed": [
      2026,
      7,
      16,
      19,
      17,
      5,
      3,
      197,
      0
    ],
    "summary": "Le républicain a beau avoir été élu deux fois à la Maison Blanche, en 2016 et 2024, il ne cesse de répéter – sans fournir de preuves – que les processus de vote américains sont corrompus au détriment de son camp.",
    "summary_detail": {
      "type": "text/html",
      "language": null,
      "base": "https://www.lemonde.fr/international/rss_full.xml",
      "value": "Le républicain a beau avoir été élu deux fois à la Maison Blanche, en 2016 et 2024, il ne cesse de répéter – sans fournir de preuves – que les processus de vote américains sont corrompus au détriment de son camp."
    },
    "id": "https://www.lemonde.fr/international/article/2026/07/16/l-allocution-de-donald-trump-va-porter-sur-la-protection-de-l-integrite-des-elections-a-l-approche-des-midterms-dit-la-maison-blanche_6723843_3210.html",
    "guidislink": true,
    "link": "https://www.lemonde.fr/international/article/2026/07/16/l-allocution-de-donald-trump-va-porter-sur-la-protection-de-l-integrite-des-elections-a-l-approche-des-midterms-dit-la-maison-blanche_6723843_3210.html",
    "links": [
      {
        "rel": "alternate",
        "type": "text/html",
        "href": "https://www.lemonde.fr/international/article/2026/07/16/l-allocution-de-donald-trump-va-porter-sur-la-protection-de-l-integrite-des-elections-a-l-approche-des-midterms-dit-la-maison-blanche_6723843_3210.html"
      }
    ],
    "media_content": [
      {
        "width": "644",
        "height": "322",
        "url": "https://img.lemde.fr/2026/07/16/450/0/5945/2972/644/322/60/0/c5f9eec_ftp-1-1zpstw5uyr1c-2026-07-16t174324z-972400445-rc25fmaj5fui-rtrmadp-3-usa-trump.JPG"
      }
    ],
    "content": [
      {
        "type": "text/plain",
        "language": null,
        "base": "https://www.lemonde.fr/international/rss_full.xml",
        "value": "La porte-parole de la Maison Blanche, Karoline Leavitt, à Washington, le 16 juillet 2026."
      }
    ],
    "media_credit": [
      {
        "scheme": "urn:ebu",
        "content": "Evan Vucci/REUTERS"
      }
    ],
    "credit": "Evan Vucci/REUTERS"
  }
}