{
  "_source": "lemonde_intl",
  "_url_collecte": "https://www.lemonde.fr/international/rss_full.xml",
  "_capte_le": "2026-07-13T17:53:52.727789+00:00",
  "_id": "6ed0e0820251",
  "brut": {
    "title": "Coupe du monde 2026 : le sélectionneur sénégalais, Pape Thiaw, limogé après l’« échec » des Lions de la Teranga",
    "title_detail": {
      "type": "text/plain",
      "language": null,
      "base": "https://www.lemonde.fr/international/rss_full.xml",
      "value": "Coupe du monde 2026 : le sélectionneur sénégalais, Pape Thiaw, limogé après l’« échec » des Lions de la Teranga"
    },
    "published": "Mon, 13 Jul 2026 18:35:40 +0200",
    "published_parsed": [
      2026,
      7,
      13,
      16,
      35,
      40,
      0,
      194,
      0
    ],
    "updated": "Mon, 13 Jul 2026 18:58:50 +0200",
    "updated_parsed": [
      2026,
      7,
      13,
      16,
      58,
      50,
      0,
      194,
      0
    ],
    "summary": "L’équipe sénégalaise a été éliminée en seizièmes de finale du Mondial face à la Belgique (3-2), alors qu’elle menait deux buts à zéro à quatre minutes de la fin réglementaire du match.",
    "summary_detail": {
      "type": "text/html",
      "language": null,
      "base": "https://www.lemonde.fr/international/rss_full.xml",
      "value": "L’équipe sénégalaise a été éliminée en seizièmes de finale du Mondial face à la Belgique (3-2), alors qu’elle menait deux buts à zéro à quatre minutes de la fin réglementaire du match."
    },
    "id": "https://www.lemonde.fr/afrique/article/2026/07/13/coupe-du-monde-2026-le-selectionneur-senegalais-pape-thiaw-limoge-apres-l-echec-des-lions-de-la-teranga_6723120_3212.html",
    "guidislink": true,
    "link": "https://www.lemonde.fr/afrique/article/2026/07/13/coupe-du-monde-2026-le-selectionneur-senegalais-pape-thiaw-limoge-apres-l-echec-des-lions-de-la-teranga_6723120_3212.html",
    "links": [
      {
        "rel": "alternate",
        "type": "text/html",
        "href": "https://www.lemonde.fr/afrique/article/2026/07/13/coupe-du-monde-2026-le-selectionneur-senegalais-pape-thiaw-limoge-apres-l-echec-des-lions-de-la-teranga_6723120_3212.html"
      }
    ],
    "media_content": [
      {
        "width": "644",
        "height": "322",
        "url": "https://img.lemde.fr/2026/07/01/0/0/4653/2326/644/322/60/0/7e9ae2c_ftp-1-lwbwuju00pwg-2026-07-01t200233z-2055634932-up1em711jo7be-rtrmadp-3-soccer-worldcup-bel-sen.JPG"
      }
    ],
    "content": [
      {
        "type": "text/plain",
        "language": null,
        "base": "https://www.lemonde.fr/international/rss_full.xml",
        "value": "Le sélectionneur du Sénégal, Pape Thiaw, avant le match contre la Belgique, au Seattle Stadium (Etats-Unis), le 1ᵉʳ juillet 2026."
      }
    ],
    "media_credit": [
      {
        "scheme": "urn:ebu",
        "content": "Albert Gea/REUTERS"
      }
    ],
    "credit": "Albert Gea/REUTERS"
  }
}