{
  "_source": "lemonde_intl",
  "_url_collecte": "https://www.lemonde.fr/international/rss_full.xml",
  "_capte_le": "2026-07-16T10:07:45.407410+00:00",
  "_id": "88554665e308",
  "brut": {
    "title": "Antoine Rajerison, le député des paysans qui brave la junte militaire au pouvoir à Madagascar",
    "title_detail": {
      "type": "text/plain",
      "language": null,
      "base": "https://www.lemonde.fr/international/rss_full.xml",
      "value": "Antoine Rajerison, le député des paysans qui brave la junte militaire au pouvoir à Madagascar"
    },
    "published": "Thu, 16 Jul 2026 09:58:43 +0200",
    "published_parsed": [
      2026,
      7,
      16,
      7,
      58,
      43,
      3,
      197,
      0
    ],
    "updated": "Thu, 16 Jul 2026 11:10:09 +0200",
    "updated_parsed": [
      2026,
      7,
      16,
      9,
      10,
      9,
      3,
      197,
      0
    ],
    "summary": "L’ingénieur agronome engagé dans la défense des populations rurales est l’une des seules voix à oser critiquer ouvertement le régime de transition dirigé par le colonel Michaël Randrianirina.",
    "summary_detail": {
      "type": "text/html",
      "language": null,
      "base": "https://www.lemonde.fr/international/rss_full.xml",
      "value": "L’ingénieur agronome engagé dans la défense des populations rurales est l’une des seules voix à oser critiquer ouvertement le régime de transition dirigé par le colonel Michaël Randrianirina."
    },
    "id": "https://www.lemonde.fr/afrique/article/2026/07/16/antoine-rajerison-le-depute-des-paysans-qui-brave-la-junte-militaire-au-pouvoir-a-madagascar_6723748_3212.html",
    "guidislink": true,
    "link": "https://www.lemonde.fr/afrique/article/2026/07/16/antoine-rajerison-le-depute-des-paysans-qui-brave-la-junte-militaire-au-pouvoir-a-madagascar_6723748_3212.html",
    "links": [
      {
        "rel": "alternate",
        "type": "text/html",
        "href": "https://www.lemonde.fr/afrique/article/2026/07/16/antoine-rajerison-le-depute-des-paysans-qui-brave-la-junte-militaire-au-pouvoir-a-madagascar_6723748_3212.html"
      }
    ],
    "media_content": [
      {
        "width": "644",
        "height": "322",
        "url": "https://img.lemde.fr/2026/07/14/604/0/6000/3000/644/322/60/0/02b2306_upload-1-wqhwxxswzvwo-photo-1.JPG"
      }
    ],
    "content": [
      {
        "type": "text/plain",
        "language": null,
        "base": "https://www.lemonde.fr/international/rss_full.xml",
        "value": "Le député Antoine Rajerison dans les locaux de sa radio, Fivoarana, à Imerintsiatosika (Madagascar), le 8 juillet 2026."
      }
    ],
    "media_credit": [
      {
        "scheme": "urn:ebu",
        "content": "GUILHEM FABRY"
      }
    ],
    "credit": "GUILHEM FABRY"
  }
}