{
  "_source": "lemonde_intl",
  "_url_collecte": "https://www.lemonde.fr/international/rss_full.xml",
  "_capte_le": "2026-07-15T10:01:39.835335+00:00",
  "_id": "d723296e1b07",
  "brut": {
    "title": "L’Iran et les Etats-Unis s’enfoncent de nouveau dans l’impasse de la guerre",
    "title_detail": {
      "type": "text/plain",
      "language": null,
      "base": "https://www.lemonde.fr/international/rss_full.xml",
      "value": "L’Iran et les Etats-Unis s’enfoncent de nouveau dans l’impasse de la guerre"
    },
    "published": "Wed, 15 Jul 2026 11:30:01 +0200",
    "published_parsed": [
      2026,
      7,
      15,
      9,
      30,
      1,
      2,
      196,
      0
    ],
    "updated": "Wed, 15 Jul 2026 11:45:19 +0200",
    "updated_parsed": [
      2026,
      7,
      15,
      9,
      45,
      19,
      2,
      196,
      0
    ],
    "summary": "Chaque camp s’enferme dans une surenchère sans issue : Téhéran ne pourra pas surmonter durablement le blocage de ses ports, et Donald Trump prend le risque de mécontenter davantage l’opinion publique à quatre mois des élections de mi-mandat. Une escalade qui fragilise encore l’économie mondiale.",
    "summary_detail": {
      "type": "text/html",
      "language": null,
      "base": "https://www.lemonde.fr/international/rss_full.xml",
      "value": "Chaque camp s’enferme dans une surenchère sans issue : Téhéran ne pourra pas surmonter durablement le blocage de ses ports, et Donald Trump prend le risque de mécontenter davantage l’opinion publique à quatre mois des élections de mi-mandat. Une escalade qui fragilise encore l’économie mondiale."
    },
    "id": "https://www.lemonde.fr/idees/article/2026/07/15/l-iran-et-les-etats-unis-s-enfoncent-de-nouveau-dans-l-impasse-de-la-guerre_6723535_3232.html",
    "guidislink": true,
    "link": "https://www.lemonde.fr/idees/article/2026/07/15/l-iran-et-les-etats-unis-s-enfoncent-de-nouveau-dans-l-impasse-de-la-guerre_6723535_3232.html",
    "links": [
      {
        "rel": "alternate",
        "type": "text/html",
        "href": "https://www.lemonde.fr/idees/article/2026/07/15/l-iran-et-les-etats-unis-s-enfoncent-de-nouveau-dans-l-impasse-de-la-guerre_6723535_3232.html"
      }
    ],
    "media_content": [
      {
        "width": "644",
        "height": "322",
        "url": "https://img.lemde.fr/2026/07/13/625/0/6000/3000/644/322/60/0/a2aa747_ftp-1-4dqavh7jmqpe-f7749da3f14147d5bb435bf757b9f679-1-f8d7c41a8156425f9811b21ebfdd60c0.jpg"
      }
    ],
    "content": [
      {
        "type": "text/plain",
        "language": null,
        "base": "https://www.lemonde.fr/international/rss_full.xml",
        "value": "Après une explosion, au large de Bandar-e Abbas (Iran), le 13 juillet 2026."
      }
    ],
    "media_credit": [
      {
        "scheme": "urn:ebu",
        "content": "Razieh Poudat/AP"
      }
    ],
    "credit": "Razieh Poudat/AP"
  }
}