{
  "_source": "lemonde_intl",
  "_url_collecte": "https://www.lemonde.fr/international/rss_full.xml",
  "_capte_le": "2026-07-16T06:16:59.432490+00:00",
  "_id": "ded720fa2c31",
  "brut": {
    "title": "EN DIRECT, guerre au Moyen-Orient : nouvelles attaques entre les Etats-Unis et l’Iran, qui dit avoir visé des sites américains en Jordanie, au Koweït et à Bahreïn",
    "title_detail": {
      "type": "text/plain",
      "language": null,
      "base": "https://www.lemonde.fr/international/rss_full.xml",
      "value": "EN DIRECT, guerre au Moyen-Orient : nouvelles attaques entre les Etats-Unis et l’Iran, qui dit avoir visé des sites américains en Jordanie, au Koweït et à Bahreïn"
    },
    "published": "Thu, 16 Jul 2026 05:53:46 +0200",
    "published_parsed": [
      2026,
      7,
      16,
      3,
      53,
      46,
      3,
      197,
      0
    ],
    "updated": "Thu, 16 Jul 2026 07:48:52 +0200",
    "updated_parsed": [
      2026,
      7,
      16,
      5,
      48,
      52,
      3,
      197,
      0
    ],
    "summary": "L’armée iranienne a annoncé, jeudi matin, avoir ciblé des installations militaires américaines en Jordanie avec des drones, selon la télévision d’Etat, après que les Etats-Unis ont mené de nouvelles frappes sur le territoire iranien.",
    "summary_detail": {
      "type": "text/html",
      "language": null,
      "base": "https://www.lemonde.fr/international/rss_full.xml",
      "value": "L’armée iranienne a annoncé, jeudi matin, avoir ciblé des installations militaires américaines en Jordanie avec des drones, selon la télévision d’Etat, après que les Etats-Unis ont mené de nouvelles frappes sur le territoire iranien."
    },
    "id": "https://www.lemonde.fr/international/live/2026/07/16/en-direct-guerre-au-moyen-orient-les-etats-unis-ont-lance-de-nouvelles-frappes-contre-l-iran-teheran-cible-des-installations-americaines-en-jordanie_6722873_3210.html",
    "guidislink": true,
    "link": "https://www.lemonde.fr/international/live/2026/07/16/en-direct-guerre-au-moyen-orient-les-etats-unis-ont-lance-de-nouvelles-frappes-contre-l-iran-teheran-cible-des-installations-americaines-en-jordanie_6722873_3210.html",
    "links": [
      {
        "rel": "alternate",
        "type": "text/html",
        "href": "https://www.lemonde.fr/international/live/2026/07/16/en-direct-guerre-au-moyen-orient-les-etats-unis-ont-lance-de-nouvelles-frappes-contre-l-iran-teheran-cible-des-installations-americaines-en-jordanie_6722873_3210.html"
      }
    ],
    "media_content": [
      {
        "width": "644",
        "height": "322",
        "url": "https://img.lemde.fr/2026/07/16/0/0/1920/960/644/322/60/0/8e0fca2_ftp-1-9vduutbwwrgd-2026-07-16t023852z-1217099177-rc2qemap3n85-rtrmadp-3-iran-crisis-usa.JPG"
      }
    ],
    "content": [
      {
        "type": "text/plain",
        "language": null,
        "base": "https://www.lemonde.fr/international/rss_full.xml",
        "value": "Du matériel militaire pris pour cible dans un lieu non précisé, lors de ce que le Commandement central américain (CENTCOM) qualifie de frappes contre l’Iran, sur cette capture d’écran tirée d’une vidéo diffusée le 15 juillet 2026."
      }
    ],
    "media_credit": [
      {
        "scheme": "urn:ebu",
        "content": "Armée américaine via REUTERS"
      }
    ],
    "credit": "Armée américaine via REUTERS"
  }
}